minihjm/__init__.py
minihjm/greet.py
tests/__init__.py
tests/test_greet.py
minihjm-0.6.0.dist-info/METADATA
minihjm-0.6.0.dist-info/WHEEL
minihjm-0.6.0.dist-info/top_level.txt
minihjm-0.6.0.dist-info/RECORD
